[
  {
    "name": "Mutton Nihari",
    "description": "Traditional Slow-cooked mutton in spicy gravy",
    "price": 1950,
    "mood": "Anytime",
    "cuisine": "Pakistani",
    "rating": 4.9
  },
  {
    "name": "Mutton Qorma",
    "description": "Homemade Mild mutton curry with yogurt",
    "price": 1850,
    "mood": "Anytime",
    "cuisine": "Pakistani",
    "rating": 4.7
  },
  {
    "name": "Beef Biryani",
    "description": "Signature Spiced rice with beef chunks",
    "price": 1050,
    "mood": "Anytime",
    "cuisine": "Pakistani",
    "rating": 4.8
  },
  {
    "name": "Chicken Nihari",
    "description": "Fresh Slow-cooked chicken in spicy gravy",
    "price": 1400,
    "mood": "Anytime",
    "cuisine": "Pakistani",
    "rating": 5.0
  },
  {
    "name": "Chicken Curry",
    "description": "Delicious Traditional chicken curry",
    "price": 1100,
    "mood": "Anytime",
    "cuisine": "Pakistani",
    "rating": 4.7
  },
  {
    "name": "Garlic Naan (2pc)",
    "description": "Premium Naan with garlic and butter",
    "price": 300,
    "mood": "Anytime",
    "cuisine": "Pakistani",
    "rating": 4.7
  }
]