[
  {
    "name": "Cortado",
    "description": "Homemade Espresso with equal parts steamed milk",
    "price": 400,
    "mood": "Anytime",
    "cuisine": "Coffee",
    "rating": 3.5
  },
  {
    "name": "Banana Bread",
    "description": "Signature Moist banana bread slice",
    "price": 300,
    "mood": "Anytime",
    "cuisine": "Coffee",
    "rating": 3.5
  },
  {
    "name": "Mocha",
    "description": "Fresh Chocolate espresso with steamed milk",
    "price": 550,
    "mood": "Anytime",
    "cuisine": "Coffee",
    "rating": 3.7
  },
  {
    "name": "Bagel with Cream Cheese",
    "description": "Delicious Fresh bagel with cream cheese",
    "price": 350,
    "mood": "Anytime",
    "cuisine": "Coffee",
    "rating": 3.5
  },
  {
    "name": "Americano",
    "description": "Premium Espresso with hot water",
    "price": 450,
    "mood": "Anytime",
    "cuisine": "Coffee",
    "rating": 3.5
  },
  {
    "name": "Cinnamon Roll",
    "description": "Special Sweet cinnamon pastry",
    "price": 400,
    "mood": "Anytime",
    "cuisine": "Coffee",
    "rating": 3.4
  }
]