[
  {
    "name": "Chicken Kofta",
    "description": "Signature Chicken meatballs in curry",
    "price": 1100,
    "mood": "Anytime",
    "cuisine": "Pakistani",
    "rating": 4.3
  },
  {
    "name": "Garlic Naan (2pc)",
    "description": "Fresh Naan with garlic and butter",
    "price": 350,
    "mood": "Anytime",
    "cuisine": "Pakistani",
    "rating": 4.5
  },
  {
    "name": "Mutton Qorma",
    "description": "Delicious Mild mutton curry with yogurt",
    "price": 1950,
    "mood": "Anytime",
    "cuisine": "Pakistani",
    "rating": 4.5
  },
  {
    "name": "Chicken Jalfrezi",
    "description": "Premium Spicy chicken with bell peppers",
    "price": 1350,
    "mood": "Anytime",
    "cuisine": "Pakistani",
    "rating": 4.3
  },
  {
    "name": "Roti (4pc)",
    "description": "Special Fresh flatbread",
    "price": 250,
    "mood": "Anytime",
    "cuisine": "Pakistani",
    "rating": 4.5
  },
  {
    "name": "Chicken Nihari",
    "description": "Authentic Slow-cooked chicken in spicy gravy",
    "price": 1500,
    "mood": "Anytime",
    "cuisine": "Pakistani",
    "rating": 4.4
  }
]