[
  {
    "name": "Mutton Nihari",
    "description": "Signature Slow-cooked mutton in spicy gravy",
    "price": 2100,
    "mood": "Anytime",
    "cuisine": "Pakistani",
    "rating": 4.7
  },
  {
    "name": "Chicken Qorma",
    "description": "Fresh Mild chicken curry with yogurt",
    "price": 1200,
    "mood": "Anytime",
    "cuisine": "Pakistani",
    "rating": 4.7
  },
  {
    "name": "Chicken Jalfrezi",
    "description": "Delicious Spicy chicken with bell peppers",
    "price": 1250,
    "mood": "Anytime",
    "cuisine": "Pakistani",
    "rating": 4.7
  },
  {
    "name": "Mutton Qorma",
    "description": "Premium Mild mutton curry with yogurt",
    "price": 1850,
    "mood": "Anytime",
    "cuisine": "Pakistani",
    "rating": 5.0
  },
  {
    "name": "Paratha Roll",
    "description": "Special Stuffed paratha with your choice of filling",
    "price": 400,
    "mood": "Anytime",
    "cuisine": "Pakistani",
    "rating": 4.9
  },
  {
    "name": "Beef Paratha Roll",
    "description": "Authentic Paratha stuffed with beef",
    "price": 550,
    "mood": "Anytime",
    "cuisine": "Pakistani",
    "rating": 4.7
  }
]