[
  {
    "id": "f50e8400-e29b-41d4-a716-446655440001",
    "content_id": "850e8400-e29b-41d4-a716-446655440001",
    "quality_level": "1080p",
    "resolution_width": 1920,
    "resolution_height": 1080,
    "file_url": "https://d3hmhlzg79k87z.cloudfront.net/movie_files/Queens.Of.Concrete.2024.2160p.4K.WEB.x265.10bit.AAC5.1-%5BYTS.MX%5D.mkv",
    "file_size_bytes": 2500000000,
    "duration_seconds": 8880.0,
    "bitrate_kbps": 2500,
    "video_codec": "H.264",
    "audio_codec": "AAC",
    "container_format": "mp4",
    "storage_bucket": "cup-streaming-content",
    "storage_key": "inception/1080p/master.mp4",
    "storage_region": "us-west-2",
    "cdn_url": "https://cdn.cupstreaming.com/inception/1080p/master.mp4",
    "is_ready": true,
    "subtitle_tracks": "[\"en\", \"es\", \"fr\", \"de\", \"it\", \"pt\", \"ru\", \"ja\", \"ko\", \"zh\"]",
    "audio_tracks": "[\"en\", \"es\", \"fr\", \"de\", \"it\", \"pt\", \"ru\", \"ja\", \"ko\", \"zh\"]",
    "available_languages": "[\"en\", \"es\", \"fr\", \"de\", \"it\", \"pt\", \"ru\", \"ja\", \"ko\", \"zh\"]"
  },
  {
    "id": "f50e8400-e29b-41d4-a716-446655440002",
    "content_id": "850e8400-e29b-41d4-a716-446655440001",
    "quality_level": "720p",
    "resolution_width": 1280,
    "resolution_height": 720,
    "file_url": "https://d3hmhlzg79k87z.cloudfront.net/iPhone+17+Pro+-+Unboxing+and+review+in+Japan+%F0%9F%87%AF%F0%9F%87%B5+-+iJustine+(360p%2C+h264).mp4",
    "file_size_bytes": 1500000000,
    "duration_seconds": 8880.0,
    "bitrate_kbps": 1500,
    "video_codec": "H.264",
    "audio_codec": "AAC",
    "container_format": "mp4",
    "storage_bucket": "cup-streaming-content",
    "storage_key": "inception/720p/master.mp4",
    "storage_region": "us-west-2",
    "cdn_url": "https://cdn.cupstreaming.com/inception/720p/master.mp4",
    "is_ready": true,
    "subtitle_tracks": "[\"en\", \"es\", \"fr\", \"de\", \"it\", \"pt\", \"ru\", \"ja\", \"ko\", \"zh\"]",
    "audio_tracks": "[\"en\", \"es\", \"fr\", \"de\", \"it\", \"pt\", \"ru\", \"ja\", \"ko\", \"zh\"]",
    "available_languages": "[\"en\", \"es\", \"fr\", \"de\", \"it\", \"pt\", \"ru\", \"ja\", \"ko\", \"zh\"]"
  },
  {
    "id": "f50e8400-e29b-41d4-a716-446655440003",
    "content_id": "850e8400-e29b-41d4-a716-446655440001",
    "quality_level": "480p",
    "resolution_width": 854,
    "resolution_height": 480,
    "file_url": "https://d3hmhlzg79k87z.cloudfront.net/movie_files/Superman.2025.2160p.4K.WEB.x265.10bit.AAC5.1-%5BYTS.MX%5D.mkv",
    "file_size_bytes": 800000000,
    "duration_seconds": 8880.0,
    "bitrate_kbps": 800,
    "video_codec": "H.264",
    "audio_codec": "AAC",
    "container_format": "mp4",
    "storage_bucket": "cup-streaming-content",
    "storage_key": "inception/480p/master.mp4",
    "storage_region": "us-west-2",
    "cdn_url": "https://cdn.cupstreaming.com/inception/480p/master.mp4",
    "is_ready": true,
    "subtitle_tracks": "[\"en\", \"es\", \"fr\", \"de\", \"it\", \"pt\", \"ru\", \"ja\", \"ko\", \"zh\"]",
    "audio_tracks": "[\"en\", \"es\", \"fr\", \"de\", \"it\", \"pt\", \"ru\", \"ja\", \"ko\", \"zh\"]",
    "available_languages": "[\"en\", \"es\", \"fr\", \"de\", \"it\", \"pt\", \"ru\", \"ja\", \"ko\", \"zh\"]"
  },
  {
    "id": "f50e8400-e29b-41d4-a716-446655440004",
    "content_id": "850e8400-e29b-41d4-a716-446655440002",
    "quality_level": "1080p",
    "resolution_width": 1920,
    "resolution_height": 1080,
    "file_url": "https://d3hmhlzg79k87z.cloudfront.net/movie_files/The.Devil.Is.Busy.2024.2160p.4K.WEB.x265.10bit.AAC5.1-%5BYTS.MX%5D.mkv",
    "file_size_bytes": 3000000000,
    "duration_seconds": 9780.0,
    "bitrate_kbps": 3000,
    "video_codec": "H.264",
    "audio_codec": "AAC",
    "container_format": "mp4",
    "storage_bucket": "cup-streaming-content",
    "storage_key": "blade-runner-2049/1080p/master.mp4",
    "storage_region": "us-west-2",
    "cdn_url": "https://cdn.cupstreaming.com/blade-runner-2049/1080p/master.mp4",
    "is_ready": true,
    "subtitle_tracks": "[\"en\", \"es\", \"fr\", \"de\", \"it\", \"pt\", \"ru\", \"ja\", \"ko\", \"zh\"]",
    "audio_tracks": "[\"en\", \"es\", \"fr\", \"de\", \"it\", \"pt\", \"ru\", \"ja\", \"ko\", \"zh\"]",
    "available_languages": "[\"en\", \"es\", \"fr\", \"de\", \"it\", \"pt\", \"ru\", \"ja\", \"ko\", \"zh\"]"
  },
  {
    "id": "f50e8400-e29b-41d4-a716-446655440005",
    "content_id": "850e8400-e29b-41d4-a716-446655440002",
    "quality_level": "720p",
    "resolution_width": 1280,
    "resolution_height": 720,
    "file_url": "https://d3hmhlzg79k87z.cloudfront.net/videoplayback.mp4",
    "file_size_bytes": 1800000000,
    "duration_seconds": 9780.0,
    "bitrate_kbps": 1800,
    "video_codec": "H.264",
    "audio_codec": "AAC",
    "container_format": "mp4",
    "storage_bucket": "cup-streaming-content",
    "storage_key": "blade-runner-2049/720p/master.mp4",
    "storage_region": "us-west-2",
    "cdn_url": "https://cdn.cupstreaming.com/blade-runner-2049/720p/master.mp4",
    "is_ready": true,
    "subtitle_tracks": "[\"en\", \"es\", \"fr\", \"de\", \"it\", \"pt\", \"ru\", \"ja\", \"ko\", \"zh\"]",
    "audio_tracks": "[\"en\", \"es\", \"fr\", \"de\", \"it\", \"pt\", \"ru\", \"ja\", \"ko\", \"zh\"]",
    "available_languages": "[\"en\", \"es\", \"fr\", \"de\", \"it\", \"pt\", \"ru\", \"ja\", \"ko\", \"zh\"]"
  },
  {
    "id": "f50e8400-e29b-41d4-a716-446655440006",
    "content_id": "850e8400-e29b-41d4-a716-446655440003",
    "quality_level": "1080p",
    "resolution_width": 1920,
    "resolution_height": 1080,
    "file_url": "https://d3hmhlzg79k87z.cloudfront.net/movie_files/The.Rundown.2003.2160p.4K.BluRay.x265.10bit.AAC5.1-%5BYTS.MX%5D.mkv",
    "file_size_bytes": 2200000000,
    "duration_seconds": 7680.0,
    "bitrate_kbps": 2200,
    "video_codec": "H.264",
    "audio_codec": "AAC",
    "container_format": "mp4",
    "storage_bucket": "cup-streaming-content",
    "storage_key": "la-la-land/1080p/master.mp4",
    "storage_region": "us-west-2",
    "cdn_url": "https://cdn.cupstreaming.com/la-la-land/1080p/master.mp4",
    "is_ready": true,
    "subtitle_tracks": "[\"en\", \"es\", \"fr\", \"de\", \"it\", \"pt\", \"ru\", \"ja\", \"ko\", \"zh\"]",
    "audio_tracks": "[\"en\", \"es\", \"fr\", \"de\", \"it\", \"pt\", \"ru\", \"ja\", \"ko\", \"zh\"]",
    "available_languages": "[\"en\", \"es\", \"fr\", \"de\", \"it\", \"pt\", \"ru\", \"ja\", \"ko\", \"zh\"]"
  },
  {
    "id": "f50e8400-e29b-41d4-a716-446655440007",
    "content_id": "850e8400-e29b-41d4-a716-446655440003",
    "quality_level": "720p",
    "resolution_width": 1280,
    "resolution_height": 720,
    "file_url": "https://d3hmhlzg79k87z.cloudfront.net/Peaky+Blinders++Season+5+Trailer++Netflix+-+Netflix+(720p%2C+h264).mp4",
    "file_size_bytes": 1300000000,
    "duration_seconds": 7680.0,
    "bitrate_kbps": 1300,
    "video_codec": "H.264",
    "audio_codec": "AAC",
    "container_format": "mp4",
    "storage_bucket": "cup-streaming-content",
    "storage_key": "la-la-land/720p/master.mp4",
    "storage_region": "us-west-2",
    "cdn_url": "https://cdn.cupstreaming.com/la-la-land/720p/master.mp4",
    "is_ready": true,
    "subtitle_tracks": "[\"en\", \"es\", \"fr\", \"de\", \"it\", \"pt\", \"ru\", \"ja\", \"ko\", \"zh\"]",
    "audio_tracks": "[\"en\", \"es\", \"fr\", \"de\", \"it\", \"pt\", \"ru\", \"ja\", \"ko\", \"zh\"]",
    "available_languages": "[\"en\", \"es\", \"fr\", \"de\", \"it\", \"pt\", \"ru\", \"ja\", \"ko\", \"zh\"]"
  },
  {
    "id": "f50e8400-e29b-41d4-a716-446655440008",
    "content_id": "850e8400-e29b-41d4-a716-446655440004",
    "quality_level": "1080p",
    "resolution_width": 1920,
    "resolution_height": 1080,
    "file_url": "https://d3hmhlzg79k87z.cloudfront.net/videoplayback.mp4",
    "file_size_bytes": 1800000000,
    "duration_seconds": 7500.0,
    "bitrate_kbps": 2000,
    "video_codec": "H.264",
    "audio_codec": "AAC",
    "container_format": "mp4",
    "storage_bucket": "cup-streaming-content",
    "storage_key": "spirited-away/1080p/master.mp4",
    "storage_region": "us-west-2",
    "cdn_url": "https://cdn.cupstreaming.com/spirited-away/1080p/master.mp4",
    "is_ready": true,
    "subtitle_tracks": "[\"en\", \"es\", \"fr\", \"de\", \"it\", \"pt\", \"ru\", \"ja\", \"ko\", \"zh\"]",
    "audio_tracks": "[\"en\", \"es\", \"fr\", \"de\", \"it\", \"pt\", \"ru\", \"ja\", \"ko\", \"zh\"]",
    "available_languages": "[\"en\", \"es\", \"fr\", \"de\", \"it\", \"pt\", \"ru\", \"ja\", \"ko\", \"zh\"]"
  },
  {
    "id": "f50e8400-e29b-41d4-a716-446655440009",
    "content_id": "850e8400-e29b-41d4-a716-446655440004",
    "quality_level": "720p",
    "resolution_width": 1280,
    "resolution_height": 720,
    "file_url": "https://d3hmhlzg79k87z.cloudfront.net/movie_files/Under.Fire.2025.2160p.4K.WEB.x265.10bit.AAC5.1-%5BYTS.MX%5D.mkv",
    "file_size_bytes": 1100000000,
    "duration_seconds": 7500.0,
    "bitrate_kbps": 1200,
    "video_codec": "H.264",
    "audio_codec": "AAC",
    "container_format": "mp4",
    "storage_bucket": "cup-streaming-content",
    "storage_key": "spirited-away/720p/master.mp4",
    "storage_region": "us-west-2",
    "cdn_url": "https://cdn.cupstreaming.com/spirited-away/720p/master.mp4",
    "is_ready": true,
    "subtitle_tracks": "[\"en\", \"es\", \"fr\", \"de\", \"it\", \"pt\", \"ru\", \"ja\", \"ko\", \"zh\"]",
    "audio_tracks": "[\"en\", \"es\", \"fr\", \"de\", \"it\", \"pt\", \"ru\", \"ja\", \"ko\", \"zh\"]",
    "available_languages": "[\"en\", \"es\", \"fr\", \"de\", \"it\", \"pt\", \"ru\", \"ja\", \"ko\", \"zh\"]"
  },
  {
    "id": "f50e8400-e29b-41d4-a716-446655440010",
    "content_id": "850e8400-e29b-41d4-a716-446655440006",
    "quality_level": "1080p",
    "resolution_width": 1920,
    "resolution_height": 1080,
    "file_url": "https://d3hmhlzg79k87z.cloudfront.net/movie_files/Under.Fire.2025.2160p.4K.WEB.x265.10bit.AAC5.1-%5BYTS.MX%5D.mkv",
    "file_size_bytes": 4000000000,
    "duration_seconds": 36000.0,
    "bitrate_kbps": 4000,
    "video_codec": "H.264",
    "audio_codec": "AAC",
    "container_format": "mp4",
    "storage_bucket": "cup-streaming-content",
    "storage_key": "planet-earth-ii/1080p/master.mp4",
    "storage_region": "us-west-2",
    "cdn_url": "https://cdn.cupstreaming.com/planet-earth-ii/1080p/master.mp4",
    "is_ready": true,
    "subtitle_tracks": "[\"en\", \"es\", \"fr\", \"de\", \"it\", \"pt\", \"ru\", \"ja\", \"ko\", \"zh\"]",
    "audio_tracks": "[\"en\", \"es\", \"fr\", \"de\", \"it\", \"pt\", \"ru\", \"ja\", \"ko\", \"zh\"]",
    "available_languages": "[\"en\", \"es\", \"fr\", \"de\", \"it\", \"pt\", \"ru\", \"ja\", \"ko\", \"zh\"]"
  },
  {
    "id": "f50e8400-e29b-41d4-a716-446655440011",
    "content_id": "850e8400-e29b-41d4-a716-446655440006",
    "quality_level": "720p",
    "resolution_width": 1280,
    "resolution_height": 720,
    "file_url": "https://d3hmhlzg79k87z.cloudfront.net/movie_files/Watchmen.Chapter.II.2024.2160p.4K.WEB.x265.10bit.AAC5.1-%5BYTS.MX%5D.mkv",
    "file_size_bytes": 2400000000,
    "duration_seconds": 36000.0,
    "bitrate_kbps": 2400,
    "video_codec": "H.264",
    "audio_codec": "AAC",
    "container_format": "mp4",
    "storage_bucket": "cup-streaming-content",
    "storage_key": "planet-earth-ii/720p/master.mp4",
    "storage_region": "us-west-2",
    "cdn_url": "https://cdn.cupstreaming.com/planet-earth-ii/720p/master.mp4",
    "is_ready": true,
    "subtitle_tracks": "[\"en\", \"es\", \"fr\", \"de\", \"it\", \"pt\", \"ru\", \"ja\", \"ko\", \"zh\"]",
    "audio_tracks": "[\"en\", \"es\", \"fr\", \"de\", \"it\", \"pt\", \"ru\", \"ja\", \"ko\", \"zh\"]",
    "available_languages": "[\"en\", \"es\", \"fr\", \"de\", \"it\", \"pt\", \"ru\", \"ja\", \"ko\", \"zh\"]"
  },
  {
    "id": "f50e8400-e29b-41d4-a716-446655440012",
    "content_id": "850e8400-e29b-41d4-a716-446655440001",
    "quality_level": "360p",
    "resolution_width": 640,
    "resolution_height": 360,
    "file_url": "https://d3hmhlzg79k87z.cloudfront.net/Peaky+Blinders+-+Season+1++Trailer+-+Alextvshows+(360p%2C+h264).mp4",
    "file_size_bytes": 500000000,
    "duration_seconds": 8880.0,
    "bitrate_kbps": 500,
    "video_codec": "H.264",
    "audio_codec": "AAC",
    "container_format": "mp4",
    "storage_bucket": "cup-streaming-content",
    "storage_key": "inception/360p/master.mp4",
    "storage_region": "us-west-2",
    "cdn_url": "https://cdn.cupstreaming.com/inception/360p/master.mp4",
    "is_ready": true,
    "subtitle_tracks": "[\"en\", \"es\", \"fr\", \"de\", \"it\", \"pt\", \"ru\", \"ja\", \"ko\", \"zh\"]",
    "audio_tracks": "[\"en\", \"es\", \"fr\", \"de\", \"it\", \"pt\", \"ru\", \"ja\", \"ko\", \"zh\"]",
    "available_languages": "[\"en\", \"es\", \"fr\", \"de\", \"it\", \"pt\", \"ru\", \"ja\", \"ko\", \"zh\"]"
  },
  {
    "id": "f50e8400-e29b-41d4-a716-446655440013",
    "content_id": "850e8400-e29b-41d4-a716-446655440002",
    "quality_level": "360p",
    "resolution_width": 640,
    "resolution_height": 360,
    "file_url": "https://d3hmhlzg79k87z.cloudfront.net/movie_files/Watchmen.Chapter.II.2024.2160p.4K.WEB.x265.10bit.AAC5.1-%5BYTS.MX%5D.mkv",
    "file_size_bytes": 600000000,
    "duration_seconds": 9780.0,
    "bitrate_kbps": 600,
    "video_codec": "H.264",
    "audio_codec": "AAC",
    "container_format": "mp4",
    "storage_bucket": "cup-streaming-content",
    "storage_key": "blade-runner-2049/360p/master.mp4",
    "storage_region": "us-west-2",
    "cdn_url": "https://cdn.cupstreaming.com/blade-runner-2049/360p/master.mp4",
    "is_ready": true,
    "subtitle_tracks": "[\"en\", \"es\", \"fr\", \"de\", \"it\", \"pt\", \"ru\", \"ja\", \"ko\", \"zh\"]",
    "audio_tracks": "[\"en\", \"es\", \"fr\", \"de\", \"it\", \"pt\", \"ru\", \"ja\", \"ko\", \"zh\"]",
    "available_languages": "[\"en\", \"es\", \"fr\", \"de\", \"it\", \"pt\", \"ru\", \"ja\", \"ko\", \"zh\"]"
  },
  {
    "id": "f50e8400-e29b-41d4-a716-446655440014",
    "content_id": "850e8400-e29b-41d4-a716-446655440003",
    "quality_level": "360p",
    "resolution_width": 640,
    "resolution_height": 360,
    "file_url": "https://d3hmhlzg79k87z.cloudfront.net/videoplayback.mp4",
    "file_size_bytes": 400000000,
    "duration_seconds": 7680.0,
    "bitrate_kbps": 400,
    "video_codec": "H.264",
    "audio_codec": "AAC",
    "container_format": "mp4",
    "storage_bucket": "cup-streaming-content",
    "storage_key": "la-la-land/360p/master.mp4",
    "storage_region": "us-west-2",
    "cdn_url": "https://cdn.cupstreaming.com/la-la-land/360p/master.mp4",
    "is_ready": true,
    "subtitle_tracks": "[\"en\", \"es\", \"fr\", \"de\", \"it\", \"pt\", \"ru\", \"ja\", \"ko\", \"zh\"]",
    "audio_tracks": "[\"en\", \"es\", \"fr\", \"de\", \"it\", \"pt\", \"ru\", \"ja\", \"ko\", \"zh\"]",
    "available_languages": "[\"en\", \"es\", \"fr\", \"de\", \"it\", \"pt\", \"ru\", \"ja\", \"ko\", \"zh\"]"
  },
  {
    "id": "f50e8400-e29b-41d4-a716-446655440015",
    "content_id": "850e8400-e29b-41d4-a716-446655440004",
    "quality_level": "360p",
    "resolution_width": 640,
    "resolution_height": 360,
    "file_url": "https://d3hmhlzg79k87z.cloudfront.net/movie_files/The.Rundown.2003.2160p.4K.BluRay.x265.10bit.AAC5.1-%5BYTS.MX%5D.mkv",
    "file_size_bytes": 450000000,
    "duration_seconds": 7500.0,
    "bitrate_kbps": 450,
    "video_codec": "H.264",
    "audio_codec": "AAC",
    "container_format": "mp4",
    "storage_bucket": "cup-streaming-content",
    "storage_key": "spirited-away/360p/master.mp4",
    "storage_region": "us-west-2",
    "cdn_url": "https://cdn.cupstreaming.com/spirited-away/360p/master.mp4",
    "is_ready": true,
    "subtitle_tracks": "[\"en\", \"es\", \"fr\", \"de\", \"it\", \"pt\", \"ru\", \"ja\", \"ko\", \"zh\"]",
    "audio_tracks": "[\"en\", \"es\", \"fr\", \"de\", \"it\", \"pt\", \"ru\", \"ja\", \"ko\", \"zh\"]",
    "available_languages": "[\"en\", \"es\", \"fr\", \"de\", \"it\", \"pt\", \"ru\", \"ja\", \"ko\", \"zh\"]"
  },
  {
    "id": "f50e8400-e29b-41d4-a716-446655440016",
    "content_id": "850e8400-e29b-41d4-a716-446655440006",
    "quality_level": "360p",
    "resolution_width": 640,
    "resolution_height": 360,
    "file_url": "https://d3hmhlzg79k87z.cloudfront.net/movie_files/The.Devil.Is.Busy.2024.2160p.4K.WEB.x265.10bit.AAC5.1-%5BYTS.MX%5D.mkv",
    "file_size_bytes": 800000000,
    "duration_seconds": 36000.0,
    "bitrate_kbps": 800,
    "video_codec": "H.264",
    "audio_codec": "AAC",
    "container_format": "mp4",
    "storage_bucket": "cup-streaming-content",
    "storage_key": "planet-earth-ii/360p/master.mp4",
    "storage_region": "us-west-2",
    "cdn_url": "https://cdn.cupstreaming.com/planet-earth-ii/360p/master.mp4",
    "is_ready": true,
    "subtitle_tracks": "[\"en\", \"es\", \"fr\", \"de\", \"it\", \"pt\", \"ru\", \"ja\", \"ko\", \"zh\"]",
    "audio_tracks": "[\"en\", \"es\", \"fr\", \"de\", \"it\", \"pt\", \"ru\", \"ja\", \"ko\", \"zh\"]",
    "available_languages": "[\"en\", \"es\", \"fr\", \"de\", \"it\", \"pt\", \"ru\", \"ja\", \"ko\", \"zh\"]"
  }
]
