{
  "restaurant_name": "Shahi Murg Chanay",
  "menu": [
    {
      "name": "Mutton Yakhni Pulao",
      "description": "Traditional Rice cooked with mutton stock",
      "price": 1050,
      "mood": "Anytime",
      "cuisine": "Pakistani",
      "rating": 4.5,
      "estimated_calories": 545
    },
    {
      "name": "Beef Kofta",
      "description": "Homemade Beef meatballs in curry",
      "price": 1250,
      "mood": "Anytime",
      "cuisine": "Pakistani",
      "rating": 4.7,
      "estimated_calories": 325
    },
    {
      "name": "Mutton Nihari",
      "description": "Signature Slow-cooked mutton in spicy gravy",
      "price": 2100,
      "mood": "Anytime",
      "cuisine": "Pakistani",
      "rating": 4.7,
      "estimated_calories": 579
    },
    {
      "name": "Mutton Karahi",
      "description": "Fresh Spicy mutton curry cooked in a wok",
      "price": 1700,
      "mood": "Anytime",
      "cuisine": "Pakistani",
      "rating": 4.8,
      "estimated_calories": 577
    },
    {
      "name": "Mutton Biryani",
      "description": "Delicious Aromatic rice with tender mutton pieces",
      "price": 1100,
      "mood": "Anytime",
      "cuisine": "Pakistani",
      "rating": 4.7,
      "estimated_calories": 585
    },
    {
      "name": "Garlic Naan (2pc)",
      "description": "Premium Naan with garlic and butter",
      "price": 250,
      "mood": "Anytime",
      "cuisine": "Pakistani",
      "rating": 4.5,
      "estimated_calories": 261
    }
  ]
}